joptional/__init__.py
joptional/optional.py
joptional-0.1.1.dist-info/METADATA
joptional-0.1.1.dist-info/WHEEL
joptional-0.1.1.dist-info/RECORD
