Metadata-Version: 2.1
Name: joptional
Version: 0.1.1
Summary: Exact implementation of Java's Optional in Python with 100% test coverage.
License: MIT
Author: Tobias Waslowski
Author-email: tobiaswaslowski@gmail.com
Requires-Python: >=3.7,<4.0
Classifier: License :: OSI Approved :: MIT License
Classifier: Programming Language :: Python :: 3
Classifier: Programming Language :: Python :: 3.7
Classifier: Programming Language :: Python :: 3.8
Classifier: Programming Language :: Python :: 3.9
Classifier: Programming Language :: Python :: 3.10
Classifier: Programming Language :: Python :: 3.11
Classifier: Programming Language :: Python :: 3.12
